{"noiseKey":{"private":{"type":"Buffer","data":"cFZEJJDYqoQWoXG3LB6eSr2Q50OzmCk2yhitB2xMskU="},"public":{"type":"Buffer","data":"7nQFux54KIsvRauxWPQNinBAu6Z+t+Ic0YiG76SEkwM="}},"pairingEphemeralKeyPair":{"private":{"type":"Buffer","data":"0K7OdZHu8Q8NppZHlhSYo1dwiynmgCe0cKn9doeTpVo="},"public":{"type":"Buffer","data":"EwBzgqV1RPbPcRXeoTrOUJ1jzbFz0Qh8X03ZBQLFZBA="}},"signedIdentityKey":{"private":{"type":"Buffer","data":"SCiIxk+9rWNPCXlevK4rxqhmORfXwdfYrVf5srQCQlI="},"public":{"type":"Buffer","data":"yeN1O3JBM+K2pxc1Oglso6waYm//pMGT8H6toBcZfhc="}},"signedPreKey":{"keyPair":{"private":{"type":"Buffer","data":"OFf/KmWeKjQnMNbYb/R8zV2Hh4o7LM0jkZGL4/q2P2w="},"public":{"type":"Buffer","data":"3suYbKMdJ512KryLHyNMBvRhg3widi78niFwLlQZkTA="}},"signature":{"type":"Buffer","data":"7pi8Ks4XlCBn7f2lEnhP9WnG58hzFkRjSvrOGGeKneg8acK4QMQn8yVosTC8+hpCsGzUdK5WW3XOTgsQkKqviA=="},"keyId":1},"registrationId":169,"advSecretKey":"+hYJfZyL5uvX6LWFD42i14CcXF5eCb8anxdKt0Q9Q18=","processedHistoryMessages":[{"key":{"remoteJid":"5214641407721@s.whatsapp.net","fromMe":true,"id":"3AF0C250DBC9FDE32391"},"messageTimestamp":1730903139},{"key":{"remoteJid":"5214641407721@s.whatsapp.net","fromMe":true,"id":"3A363BBAA59A090EA288"},"messageTimestamp":1730903140},{"key":{"remoteJid":"5214641407721@s.whatsapp.net","fromMe":true,"id":"3AA608D7ECEE4D0D5F0B"},"messageTimestamp":1730903843},{"key":{"remoteJid":"5214641407721@s.whatsapp.net","fromMe":true,"id":"3A48ED8CDD73065D8D15"},"messageTimestamp":1730904745},{"key":{"remoteJid":"5214641407721@s.whatsapp.net","fromMe":true,"id":"3ADA23A6E493252AA081"},"messageTimestamp":1730904745}],"nextPreKeyId":31,"firstUnuploadedPreKeyId":31,"accountSyncCounter":1,"accountSettings":{"unarchiveChats":false},"deviceId":"XGyC_AuERIS2bfA5pWy9tg","phoneId":"2378485f-4299-418d-aa45-70c7bb19a960","identityId":{"type":"Buffer","data":"7NO3YcG5NqpwyYqYhX/OGnNrRsE="},"registered":false,"backupToken":{"type":"Buffer","data":"YYO00xoeE3yht7IcfOpHWE9FBMQ="},"registration":{},"account":{"details":"CK7UvLwHEN74rbkGGBogACgA","accountSignatureKey":"4KNUwHPw0f25kqgTwn5teAT5uSHe6uFoQpSMmYggKFk=","accountSignature":"0Tfz1wijpFIFzLFdGyR1rQbXMHTLbg7CDsrVFweju41EsuyN5PhJsOmNjWO3tytNnfScEAQaR4xZ7AfMDO9Fgw==","deviceSignature":"itxvYdfsDjTAJOriz0sRZfbmNLg0Mr+CxL1oMxIhQammwk5BZv1XLxEHSTto3XEFqwdogcXU2Xoccm/MRMPlgA=="},"me":{"id":"5214641407721:35@s.whatsapp.net","name":"Martin ✇"},"signalIdentities":[{"identifier":{"name":"5214641407721:35@s.whatsapp.net","deviceId":0},"identifierKey":{"type":"Buffer","data":"BeCjVMBz8NH9uZKoE8J+bXgE+bkh3urhaEKUjJmIIChZ"}}],"platform":"iphone","lastAccountSyncTimestamp":1730903136,"myAppStateKeyId":"AAAAAA6K"}